nian/__init__.py
nian-1.9.2.dist-info/LICENSE
nian-1.9.2.dist-info/METADATA
nian-1.9.2.dist-info/WHEEL
nian-1.9.2.dist-info/top_level.txt
nian-1.9.2.dist-info/RECORD
