Metadata-Version: 2.1
Name: nian
Version: 1.9.2
Summary: 测试版本，音乐爬取
Home-page: http://None/
Author: 初慕苏流年
Author-email: 1274210585@qq.com
License: UNKNOWN
Platform: UNKNOWN
Classifier: Programming Language :: Python :: 3
Classifier: License :: OSI Approved :: Apache Software License
Classifier: Operating System :: OS Independent
Requires-Python: >=3.0
License-File: LICENSE
